lumyn_sdk-4.1.1.dist-info/RECORD
lumyn_sdk-4.1.1.dist-info/WHEEL
lumyn_sdk-4.1.1.dist-info/top_level.txt
lumyn_sdk-4.1.1.dist-info/METADATA
lumyn_sdk-4.1.1.dist-info/licenses/LICENSE
lumyn_sdk/liblumyn_sdk_cpp.4.dylib
lumyn_sdk/command.pyi
lumyn_sdk/connectorx.pyi
lumyn_sdk/enums.py
lumyn_sdk/liblumyn_sdk_cpp.4.1.4.dylib
lumyn_sdk/__init__.pyi
lumyn_sdk/__init__.py
lumyn_sdk/util.pyi
lumyn_sdk/_bindings_ext.cpython-311-darwin.so
lumyn_sdk/event.pyi
lumyn_sdk/py.typed
lumyn_sdk/liblumyn_sdk_cpp.dylib
lumyn_sdk/_bindings_ext.cpython-310-darwin.so
lumyn_sdk/serial_adapter/pyserialio.py
lumyn_sdk/serial_adapter/__init__.py
lumyn_sdk/util/__init__.py
lumyn_sdk/util/serial_io.py
lumyn_sdk/util/transmission_listener.py
lumyn_sdk/util/serial/__init__.py
lumyn_sdk/util/serial/delta_compressor.pyi
lumyn_sdk/util/serial/delta_compressor.py
lumyn_sdk/_bindings/__init__.pyi
lumyn_sdk/_bindings/__init__.py
lumyn_sdk/_bindings/config.pyi
lumyn_sdk/modules/custom.py
lumyn_sdk/modules/analog_input.py
lumyn_sdk/modules/__init__.py
lumyn_sdk/modules/digital_input.py
lumyn_sdk/modules/vl53l1x.py
lumyn_sdk/domain/__init__.py
lumyn_sdk/domain/led/led_handler.py
lumyn_sdk/domain/led/__init__.py
lumyn_sdk/domain/led/direct_led.py
lumyn_sdk/domain/led/direct_led.pyi
lumyn_sdk/domain/led/led_handler.pyi
lumyn_sdk/domain/config/builders.py
lumyn_sdk/domain/config/enums.py
lumyn_sdk/domain/config/models.py
lumyn_sdk/domain/config/__init__.py
lumyn_sdk/domain/config/_python_wrapper.py
lumyn_sdk/domain/config/serialization.py
lumyn_sdk/domain/module/module_base.py
lumyn_sdk/domain/module/module_handler.pyi
lumyn_sdk/domain/module/__init__.py
lumyn_sdk/domain/module/new_data_info.py
lumyn_sdk/domain/module/module_handler.py
lumyn_sdk/domain/module/module_data_dispatcher.py
lumyn_sdk/domain/event/event.py
lumyn_sdk/domain/event/event_converter.py
lumyn_sdk/domain/event/__init__.py
lumyn_sdk/interfaces/i_event_callback.py
lumyn_sdk/interfaces/__init__.py
lumyn_sdk/interfaces/i_module_data_callback.py
lumyn_sdk/devices/connectorx_animate.pyi
lumyn_sdk/devices/connectorx_base.py
lumyn_sdk/devices/connectorx.py
