Metadata-Version: 2.4
Name: lumyn-sdk
Version: 4.1.1
Summary: Python SDK for Lumyn Labs ConnectorX LED controllers
Author: Lumyn Labs
Author-email: Lumyn Labs <support@lumynlabs.com>
License: Proprietary
Project-URL: Homepage, https://lumynlabs.com
Project-URL: Documentation, https://docs.lumynlabs.com
Project-URL: Repository, https://github.com/Lumyn-Labs/lumyn-sdk-python
Project-URL: Issues, https://github.com/Lumyn-Labs/lumyn-sdk-python/issues
Keywords: lumyn,connectorx,led,frc,robotics,animation
Classifier: Development Status :: 4 - Beta
Classifier: Intended Audience :: Developers
Classifier: License :: Other/Proprietary License
Classifier: Operating System :: OS Independent
Classifier: Programming Language :: Python :: 3
Classifier: Programming Language :: Python :: 3.8
Classifier: Programming Language :: Python :: 3.9
Classifier: Programming Language :: Python :: 3.10
Classifier: Programming Language :: Python :: 3.11
Classifier: Programming Language :: Python :: 3.12
Classifier: Topic :: Software Development :: Libraries :: Python Modules
Classifier: Topic :: System :: Hardware
Requires-Python: >=3.8
License-File: LICENSE
Requires-Dist: pyserial>=3.5
Dynamic: author
Dynamic: license-file
Dynamic: requires-python
